[{"hp":11,"atk":4,"spa":4,"def":3,"spd":3},{"hp":12,"atk":5,"spa":5,"def":4,"spd":4},{"hp":13,"atk":6,"spa":6,"def":4,"spd":4},{"hp":14,"atk":6,"spa":6,"def":5,"spd":5},{"hp":15,"atk":7,"spa":7,"def":5,"spd":5},{"hp":16,"atk":7,"spa":7,"def":6,"spd":6},{"hp":17,"atk":8,"spa":8,"def":6,"spd":6},{"hp":18,"atk":9,"spa":9,"def":7,"spd":7},{"hp":19,"atk":10,"spa":10,"def":7,"spd":7},{"hp":21,"atk":11,"spa":11,"def":8,"spd":8},{"hp":23,"atk":12,"spa":12,"def":9,"spd":9},{"hp":25,"atk":13,"spa":13,"def":10,"spd":10},{"hp":27,"atk":14,"spa":14,"def":11,"spd":11},{"hp":29,"atk":15,"spa":15,"def":12,"spd":12},{"hp":31,"atk":16,"spa":16,"def":13,"spd":13},{"hp":33,"atk":17,"spa":17,"def":14,"spd":14},{"hp":35,"atk":18,"spa":18,"def":15,"spd":15},{"hp":37,"atk":19,"spa":19,"def":16,"spd":16},{"hp":39,"atk":20,"spa":20,"def":17,"spd":17},{"hp":41,"atk":22,"spa":22,"def":19,"spd":19},{"hp":43,"atk":24,"spa":24,"def":21,"spd":21},{"hp":45,"atk":26,"spa":26,"def":23,"spd":23},{"hp":47,"atk":28,"spa":28,"def":25,"spd":25},{"hp":49,"atk":30,"spa":30,"def":27,"spd":27},{"hp":51,"atk":32,"spa":32,"def":29,"spd":29},{"hp":53,"atk":34,"spa":34,"def":31,"spd":31},{"hp":55,"atk":36,"spa":36,"def":33,"spd":33},{"hp":57,"atk":38,"spa":38,"def":35,"spd":35},{"hp":59,"atk":40,"spa":40,"def":37,"spd":37},{"hp":61,"atk":42,"spa":42,"def":39,"spd":39},{"hp":63,"atk":43,"spa":43,"def":40,"spd":40},{"hp":65,"atk":44,"spa":44,"def":41,"spd":41},{"hp":67,"atk":45,"spa":45,"def":42,"spd":42},{"hp":69,"atk":46,"spa":46,"def":43,"spd":43},{"hp":71,"atk":47,"spa":47,"def":44,"spd":44},{"hp":73,"atk":48,"spa":48,"def":45,"spd":45},{"hp":75,"atk":49,"spa":49,"def":46,"spd":46},{"hp":77,"atk":50,"spa":50,"def":47,"spd":47},{"hp":79,"atk":51,"spa":51,"def":48,"spd":48},{"hp":81,"atk":52,"spa":52,"def":49,"spd":49},{"hp":82,"atk":53,"spa":53,"def":50,"spd":50},{"hp":83,"atk":54,"spa":54,"def":51,"spd":51},{"hp":84,"atk":55,"spa":55,"def":52,"spd":52},{"hp":85,"atk":56,"spa":56,"def":53,"spd":53},{"hp":86,"atk":57,"spa":57,"def":54,"spd":54},{"hp":87,"atk":58,"spa":58,"def":55,"spd":55},{"hp":88,"atk":59,"spa":59,"def":56,"spd":56},{"hp":89,"atk":60,"spa":60,"def":57,"spd":57},{"hp":90,"atk":61,"spa":61,"def":58,"spd":58},{"hp":91,"atk":62,"spa":62,"def":59,"spd":59},{"hp":91,"atk":63,"spa":62,"def":60,"spd":60},{"hp":92,"atk":63,"spa":63,"def":61,"spd":61},{"hp":92,"atk":64,"spa":63,"def":62,"spd":62},{"hp":93,"atk":64,"spa":64,"def":63,"spd":63},{"hp":93,"atk":65,"spa":64,"def":64,"spd":64},{"hp":94,"atk":65,"spa":65,"def":65,"spd":65},{"hp":94,"atk":66,"spa":65,"def":66,"spd":66},{"hp":95,"atk":66,"spa":66,"def":67,"spd":67},{"hp":95,"atk":67,"spa":66,"def":68,"spd":68},{"hp":96,"atk":68,"spa":67,"def":69,"spd":69},{"hp":97,"atk":69,"spa":68,"def":70,"spd":70},{"hp":98,"atk":70,"spa":69,"def":71,"spd":71},{"hp":99,"atk":71,"spa":70,"def":72,"spd":72},{"hp":100,"atk":72,"spa":71,"def":73,"spd":73},{"hp":101,"atk":73,"spa":72,"def":74,"spd":74},{"hp":102,"atk":74,"spa":73,"def":75,"spd":75},{"hp":103,"atk":75,"spa":74,"def":76,"spd":76},{"hp":104,"atk":76,"spa":75,"def":77,"spd":77},{"hp":105,"atk":77,"spa":76,"def":78,"spd":78},{"hp":106,"atk":78,"spa":77,"def":79,"spd":79},{"hp":107,"atk":79,"spa":78,"def":80,"spd":80},{"hp":108,"atk":80,"spa":79,"def":81,"spd":81},{"hp":109,"atk":81,"spa":80,"def":82,"spd":82},{"hp":110,"atk":82,"spa":81,"def":83,"spd":83},{"hp":111,"atk":83,"spa":82,"def":84,"spd":84},{"hp":112,"atk":84,"spa":83,"def":85,"spd":85},{"hp":113,"atk":85,"spa":84,"def":86,"spd":86},{"hp":114,"atk":86,"spa":85,"def":87,"spd":87},{"hp":115,"atk":87,"spa":86,"def":88,"spd":88},{"hp":116,"atk":88,"spa":87,"def":89,"spd":89},{"hp":117,"atk":89,"spa":88,"def":90,"spd":90},{"hp":118,"atk":90,"spa":89,"def":91,"spd":91},{"hp":119,"atk":91,"spa":90,"def":92,"spd":92},{"hp":120,"atk":92,"spa":91,"def":93,"spd":93},{"hp":121,"atk":93,"spa":92,"def":94,"spd":94},{"hp":122,"atk":94,"spa":93,"def":95,"spd":95},{"hp":123,"atk":95,"spa":94,"def":96,"spd":96},{"hp":124,"atk":96,"spa":95,"def":97,"spd":97},{"hp":125,"atk":97,"spa":96,"def":98,"spd":98},{"hp":126,"atk":98,"spa":97,"def":99,"spd":99},{"hp":127,"atk":99,"spa":98,"def":100,"spd":100},{"hp":128,"atk":100,"spa":99,"def":101,"spd":101},{"hp":129,"atk":101,"spa":100,"def":102,"spd":102},{"hp":130,"atk":102,"spa":101,"def":103,"spd":103},{"hp":131,"atk":103,"spa":102,"def":104,"spd":104},{"hp":132,"atk":104,"spa":103,"def":105,"spd":105},{"hp":133,"atk":105,"spa":104,"def":106,"spd":106},{"hp":134,"atk":106,"spa":105,"def":107,"spd":107},{"hp":135,"atk":107,"spa":106,"def":108,"spd":108},{"hp":136,"atk":108,"spa":107,"def":109,"spd":109}]