[{"hp":35,"atk":17,"spa":5,"def":25,"spd":12},{"hp":37,"atk":18,"spa":6,"def":26,"spd":12},{"hp":39,"atk":19,"spa":7,"def":26,"spd":13},{"hp":41,"atk":20,"spa":8,"def":27,"spd":13},{"hp":43,"atk":21,"spa":9,"def":27,"spd":14},{"hp":45,"atk":22,"spa":10,"def":28,"spd":14},{"hp":47,"atk":23,"spa":11,"def":28,"spd":15},{"hp":49,"atk":24,"spa":12,"def":29,"spd":15},{"hp":51,"atk":25,"spa":13,"def":29,"spd":16},{"hp":53,"atk":26,"spa":14,"def":30,"spd":16},{"hp":55,"atk":27,"spa":15,"def":30,"spd":17},{"hp":57,"atk":28,"spa":16,"def":31,"spd":17},{"hp":59,"atk":29,"spa":17,"def":31,"spd":18},{"hp":61,"atk":30,"spa":18,"def":32,"spd":18},{"hp":63,"atk":31,"spa":19,"def":32,"spd":19},{"hp":65,"atk":32,"spa":20,"def":33,"spd":19},{"hp":67,"atk":33,"spa":21,"def":33,"spd":20},{"hp":69,"atk":34,"spa":22,"def":34,"spd":20},{"hp":71,"atk":35,"spa":23,"def":34,"spd":21},{"hp":74,"atk":36,"spa":24,"def":35,"spd":22},{"hp":77,"atk":37,"spa":25,"def":36,"spd":23},{"hp":80,"atk":38,"spa":26,"def":37,"spd":24},{"hp":83,"atk":39,"spa":27,"def":38,"spd":25},{"hp":86,"atk":40,"spa":28,"def":39,"spd":26},{"hp":89,"atk":41,"spa":29,"def":40,"spd":27},{"hp":92,"atk":42,"spa":30,"def":41,"spd":28},{"hp":96,"atk":43,"spa":31,"def":41,"spd":29},{"hp":100,"atk":44,"spa":32,"def":43,"spd":30},{"hp":103,"atk":46,"spa":32,"def":43,"spd":32},{"hp":105,"atk":46,"spa":34,"def":45,"spd":32},{"hp":107,"atk":48,"spa":34,"def":45,"spd":34},{"hp":109,"atk":48,"spa":36,"def":47,"spd":34},{"hp":111,"atk":50,"spa":36,"def":47,"spd":36},{"hp":113,"atk":50,"spa":38,"def":49,"spd":36},{"hp":115,"atk":52,"spa":38,"def":49,"spd":38},{"hp":117,"atk":52,"spa":40,"def":51,"spd":38},{"hp":119,"atk":54,"spa":40,"def":51,"spd":40},{"hp":121,"atk":54,"spa":42,"def":53,"spd":40},{"hp":123,"atk":56,"spa":42,"def":53,"spd":42},{"hp":125,"atk":56,"spa":44,"def":55,"spd":42},{"hp":127,"atk":58,"spa":44,"def":55,"spd":44},{"hp":129,"atk":58,"spa":46,"def":57,"spd":44},{"hp":131,"atk":60,"spa":46,"def":57,"spd":46},{"hp":133,"atk":60,"spa":48,"def":59,"spd":46},{"hp":135,"atk":62,"spa":48,"def":59,"spd":48},{"hp":137,"atk":62,"spa":50,"def":61,"spd":48},{"hp":139,"atk":64,"spa":50,"def":61,"spd":50},{"hp":141,"atk":64,"spa":52,"def":63,"spd":50},{"hp":143,"atk":66,"spa":52,"def":63,"spd":52},{"hp":145,"atk":66,"spa":54,"def":65,"spd":52},{"hp":147,"atk":68,"spa":54,"def":65,"spd":54},{"hp":149,"atk":68,"spa":56,"def":67,"spd":54},{"hp":151,"atk":70,"spa":56,"def":67,"spd":56},{"hp":153,"atk":70,"spa":58,"def":69,"spd":56},{"hp":155,"atk":72,"spa":58,"def":69,"spd":58},{"hp":157,"atk":72,"spa":60,"def":71,"spd":58},{"hp":159,"atk":74,"spa":60,"def":71,"spd":60},{"hp":161,"atk":74,"spa":62,"def":73,"spd":60},{"hp":163,"atk":76,"spa":62,"def":73,"spd":62},{"hp":164,"atk":77,"spa":63,"def":74,"spd":63},{"hp":165,"atk":78,"spa":64,"def":75,"spd":64},{"hp":166,"atk":79,"spa":65,"def":76,"spd":65},{"hp":167,"atk":80,"spa":66,"def":77,"spd":66},{"hp":168,"atk":81,"spa":67,"def":78,"spd":67},{"hp":169,"atk":82,"spa":68,"def":79,"spd":68},{"hp":170,"atk":83,"spa":69,"def":80,"spd":69},{"hp":171,"atk":84,"spa":70,"def":81,"spd":70},{"hp":172,"atk":85,"spa":71,"def":82,"spd":71},{"hp":173,"atk":86,"spa":72,"def":83,"spd":72},{"hp":174,"atk":87,"spa":73,"def":84,"spd":73},{"hp":175,"atk":88,"spa":74,"def":85,"spd":74},{"hp":176,"atk":89,"spa":75,"def":86,"spd":75},{"hp":177,"atk":90,"spa":76,"def":87,"spd":76},{"hp":178,"atk":91,"spa":77,"def":88,"spd":77},{"hp":179,"atk":92,"spa":78,"def":89,"spd":78},{"hp":180,"atk":93,"spa":79,"def":90,"spd":79},{"hp":181,"atk":94,"spa":80,"def":91,"spd":80},{"hp":182,"atk":95,"spa":81,"def":92,"spd":81},{"hp":183,"atk":96,"spa":82,"def":93,"spd":82},{"hp":184,"atk":97,"spa":83,"def":94,"spd":83},{"hp":185,"atk":98,"spa":84,"def":95,"spd":84},{"hp":186,"atk":99,"spa":85,"def":96,"spd":85},{"hp":187,"atk":100,"spa":86,"def":97,"spd":86},{"hp":188,"atk":101,"spa":87,"def":98,"spd":87},{"hp":189,"atk":102,"spa":88,"def":99,"spd":88},{"hp":190,"atk":103,"spa":89,"def":100,"spd":89},{"hp":191,"atk":104,"spa":90,"def":101,"spd":90},{"hp":192,"atk":105,"spa":91,"def":102,"spd":91},{"hp":193,"atk":106,"spa":92,"def":103,"spd":92},{"hp":194,"atk":107,"spa":93,"def":104,"spd":93},{"hp":195,"atk":108,"spa":94,"def":105,"spd":94},{"hp":196,"atk":109,"spa":95,"def":106,"spd":95},{"hp":197,"atk":110,"spa":96,"def":107,"spd":96},{"hp":198,"atk":111,"spa":97,"def":108,"spd":97},{"hp":199,"atk":112,"spa":98,"def":109,"spd":98},{"hp":200,"atk":113,"spa":99,"def":110,"spd":99},{"hp":201,"atk":114,"spa":100,"def":111,"spd":100},{"hp":202,"atk":115,"spa":101,"def":112,"spd":101},{"hp":203,"atk":116,"spa":102,"def":113,"spd":102},{"hp":204,"atk":117,"spa":103,"def":114,"spd":103}]